rev_tun/__init__.py
rev_tun/cli.py
rev_tun/config.py
rev_tun/const.py
rev_tun/register.py
rev_tun/utils.py
rev_tun-0.1.1.dist-info/METADATA
rev_tun-0.1.1.dist-info/WHEEL
rev_tun-0.1.1.dist-info/entry_points.txt
rev_tun-0.1.1.dist-info/top_level.txt
rev_tun-0.1.1.dist-info/RECORD
