Metadata-Version: 2.2
Name: rev-tun
Version: 0.1.1
Summary: Tool to manage ssh reverse tunnels with ease
Author-email: observerw <wozluohd@gmail.com>
Project-URL: Repository, https://github.com/observerw/rev-tun
Requires-Python: >=3.12
Requires-Dist: deepmerge>=2.0
Requires-Dist: jinja2>=3.1.5
Requires-Dist: pydantic>=2.10.5
Requires-Dist: rich>=13.9.4
Requires-Dist: tomli>=2.2.1
Requires-Dist: typer-slim>=0.15.1
